MANIFEST.in
setup.py
cmsplugin_tabs/__init__.py
cmsplugin_tabs/cms_plugins.py
cmsplugin_tabs/models.py
cmsplugin_tabs/tests.py
cmsplugin_tabs.egg-info/PKG-INFO
cmsplugin_tabs.egg-info/SOURCES.txt
cmsplugin_tabs.egg-info/dependency_links.txt
cmsplugin_tabs.egg-info/not-zip-safe
cmsplugin_tabs.egg-info/requires.txt
cmsplugin_tabs.egg-info/top_level.txt
cmsplugin_tabs/migrations/0001_initial.py
cmsplugin_tabs/migrations/0002_update_related_name.py
cmsplugin_tabs/migrations/__init__.py
cmsplugin_tabs/south_migrations/0001_initial.py
cmsplugin_tabs/south_migrations/__init__.py
cmsplugin_tabs/templates/.DS_Store
cmsplugin_tabs/templates/cmsplugin_tabs/tab.html
cmsplugin_tabs/templates/cmsplugin_tabs/tabheader.html
requirements/common.txt
requirements/testing.txt
tests/__init__.py
tests/settings.py